{
    "country":[
        {
            "code":"United States of America",
            "country":"United States of America",
            "total":"126" ,
            "gold":"40",
            "silver":"44",
            "bronze":"42"
        },
        {
            "code":"People's Republic of China",
            "country":"People's Republic of China",
            "total":"91",
            "gold":"40",
            "silver":"27",
            "bronze":"24"
        },
        {
            "code":"Japan",
            "country":"Japan",
            "total":"45",
            "gold":"20",
            "silver":"12",
            "bronze":"13"
        },
        {
            "code":"Australia",
            "country":"Australia",
            "total":"53",
            "gold":"18",
            "silver":"19",
            "bronze":"16"
        },        
        {
            "code":"France",
            "country":"France",
            "total":"64",
            "gold":"16",
            "silver":"26",
            "bronze":"22"
        },        
        {
            "code":"Netherlands",
            "country":"Netherlands",
            "total":"34",
            "gold":"15",
            "silver":"7",
            "bronze":"12"
        },       
        {
            "code":"Great Britain",
            "country":"Great Britain",
            "total":"65",
            "gold":"14",
            "silver":"22",
            "bronze":"29"
        },        
        {
            "code":"Republic of Korea",
            "country":"Republic of Korea",
            "total":"32",
            "gold":"13",
            "silver":"9",
            "bronze":"10"
        },        
        {
            "code":"Italy",
            "country":"Italy",
            "total":"40",
            "gold":"12",
            "silver":"13",
            "bronze":"15"
        }
    ]
}